cloudcoil/models/fluxcd/__init__.py
cloudcoil/models/fluxcd/py.typed
cloudcoil/models/fluxcd/helm/__init__.py
cloudcoil/models/fluxcd/helm/v2.py
cloudcoil/models/fluxcd/helm/v2beta1.py
cloudcoil/models/fluxcd/helm/v2beta2.py
cloudcoil/models/fluxcd/image/__init__.py
cloudcoil/models/fluxcd/image/v1beta1.py
cloudcoil/models/fluxcd/image/v1beta2.py
cloudcoil/models/fluxcd/kustomize/__init__.py
cloudcoil/models/fluxcd/kustomize/v1.py
cloudcoil/models/fluxcd/kustomize/v1beta1.py
cloudcoil/models/fluxcd/kustomize/v1beta2.py
cloudcoil/models/fluxcd/notification/__init__.py
cloudcoil/models/fluxcd/notification/v1.py
cloudcoil/models/fluxcd/notification/v1beta1.py
cloudcoil/models/fluxcd/notification/v1beta2.py
cloudcoil/models/fluxcd/notification/v1beta3.py
cloudcoil/models/fluxcd/source/__init__.py
cloudcoil/models/fluxcd/source/v1.py
cloudcoil/models/fluxcd/source/v1beta1.py
cloudcoil/models/fluxcd/source/v1beta2.py
cloudcoil_models_fluxcd-2.5.1.0.dist-info/METADATA
cloudcoil_models_fluxcd-2.5.1.0.dist-info/WHEEL
cloudcoil_models_fluxcd-2.5.1.0.dist-info/licenses/LICENSE
cloudcoil_models_fluxcd-2.5.1.0.dist-info/RECORD
